spacestep_tool_call/__init__.py
spacestep_tool_call/call_management.py
spacestep_tool_call/py.typed
spacestep_tool_call/scheduling.py
spacestep_tool_call-0.1.0.dist-info/licenses/LICENSE
spacestep_tool_call-0.1.0.dist-info/METADATA
spacestep_tool_call-0.1.0.dist-info/WHEEL
spacestep_tool_call-0.1.0.dist-info/top_level.txt
spacestep_tool_call-0.1.0.dist-info/RECORD
