Metadata-Version: 2.4
Name: spacestep-tool-call
Version: 0.1.0
Summary: SpaceStep Tool Call
Author-email: SpaceStep <taras@spacestep.ca>
Maintainer-email: SpaceStep <taras@spacestep.ca>
License-Expression: MIT
Project-URL: Homepage, https://github.com/spacestep/spacestep-tool-call
Project-URL: Repository, https://github.com/spacestep/spacestep-tool-call
Project-URL: Documentation, https://github.com/spacestep/spacestep-tool-call#readme
Project-URL: Bug Tracker, https://github.com/spacestep/spacestep-tool-call/issues
Keywords: spacestep,call-center,scheduling,automation,voice-agent,appointments,ai,tool-call
Classifier: Development Status :: 4 - Beta
Classifier: Intended Audience :: Developers
Classifier: Operating System :: OS Independent
Classifier: Programming Language :: Python :: 3
Classifier: Programming Language :: Python :: 3.8
Classifier: Programming Language :: Python :: 3.9
Classifier: Programming Language :: Python :: 3.10
Classifier: Programming Language :: Python :: 3.11
Classifier: Programming Language :: Python :: 3.12
Classifier: Topic :: Communications :: Telephony
Classifier: Topic :: Office/Business :: Scheduling
Classifier: Topic :: Software Development :: Libraries :: Python Modules
Requires-Python: >=3.8
License-File: LICENSE
Requires-Dist: aiohttp>=3.8.0
Requires-Dist: httpx>=0.23.0
Requires-Dist: python-dotenv>=0.21.0
Provides-Extra: dev
Requires-Dist: pytest>=7.0.0; extra == "dev"
Requires-Dist: pytest-asyncio>=0.21.0; extra == "dev"
Requires-Dist: pytest-cov>=4.0.0; extra == "dev"
Requires-Dist: black>=23.0.0; extra == "dev"
Requires-Dist: isort>=5.12.0; extra == "dev"
Requires-Dist: flake8>=6.0.0; extra == "dev"
Requires-Dist: mypy>=1.0.0; extra == "dev"
Provides-Extra: test
Requires-Dist: pytest>=7.0.0; extra == "test"
Requires-Dist: pytest-asyncio>=0.21.0; extra == "test"
Requires-Dist: pytest-cov>=4.0.0; extra == "test"
Dynamic: license-file
